smart_reid/__init__.py
smart_reid/basetrack.py
smart_reid/core.py
smart_reid/embed.py
smart_reid/kalman_filter.py
smart_reid/matching.py
smart_reid/sam_cost.py
smart_reid/strack.py
smart_reid-0.1.7.dist-info/METADATA
smart_reid-0.1.7.dist-info/WHEEL
smart_reid-0.1.7.dist-info/top_level.txt
smart_reid-0.1.7.dist-info/RECORD
