Metadata-Version: 2.1
Name: smart_reid
Version: 0.1.7
Summary: With no prior knowledge of machine learning or device-specific deployment, you can deploy a computer vision model to a range of devices and environments using Roboflow Inference CLI.
Home-page: https://github.com/roboflow/inference
Author: Roboflow
Author-email: help@roboflow.com
Classifier: Intended Audience :: Developers
Classifier: Intended Audience :: Education
Classifier: Intended Audience :: Science/Research
Classifier: License :: OSI Approved :: Apache Software License
Classifier: Programming Language :: Python :: 3
Classifier: Programming Language :: Python :: 3 :: Only
Classifier: Topic :: Software Development
Classifier: Topic :: Scientific/Engineering
Classifier: Topic :: Scientific/Engineering :: Artificial Intelligence
Classifier: Topic :: Scientific/Engineering :: Image Recognition
Classifier: Typing :: Typed
Classifier: Operating System :: OS Independent
Requires-Python: >=3.8,<=3.12
Requires-Dist: supervision==0.22.0
Requires-Dist: numpy==1.26.4
Requires-Dist: pydantic==2.8.2
Requires-Dist: typing==3.7.4.3
Requires-Dist: scipy==1.14.0
Requires-Dist: open-clip-torch==2.26.1
Requires-Dist: timm==1.0.8
Requires-Dist: torch==2.4.0
Requires-Dist: mediapipe==0.10.14
Requires-Dist: super-image==0.1.7
Requires-Dist: image_similarity_measures==0.3.6
Requires-Dist: huggingface-hub==0.24.6
